{"downloader/request_bytes": 1625020, "downloader/request_count": 3299, "downloader/request_method_count/GET": 3299, "downloader/response_bytes": 20407472, "downloader/response_count": 3299, "downloader/response_status_count/200": 2103, "downloader/response_status_count/301": 2, "downloader/response_status_count/302": 1192, "downloader/response_status_count/500": 2, "dupefilter/filtered": 7160, "elapsed_time_seconds": 20098.288139, "finish_reason": "finished", "finish_time": "2020-11-25 14:01:45.878231", "item_scraped_count": 54, "log_count/DEBUG": 3354, "log_count/INFO": 344, "memusage/max": 77705216, "memusage/startup": 64770048, "request_depth_max": 21, "response_received_count": 2103, "retry/count": 2, "retry/reason_count/500 Internal Server Error": 2, "robotstxt/request_count": 1, "robotstxt/response_count": 1, "robotstxt/response_status_count/200": 1, "scheduler/dequeued": 3298, "scheduler/dequeued/memory": 3298, "scheduler/enqueued": 3298, "scheduler/enqueued/memory": 3298, "start_time": "2020-11-25 08:26:47.590092"}