{"downloader/exception_count": 271, "downloader/exception_type_count/scrapy.exceptions.IgnoreRequest": 271, "downloader/request_bytes": 23965326, "downloader/request_count": 54324, "downloader/request_method_count/GET": 54324, "downloader/response_bytes": 891417460, "downloader/response_count": 54324, "downloader/response_status_count/200": 54272, "downloader/response_status_count/301": 46, "downloader/response_status_count/302": 1, "downloader/response_status_count/404": 5, "dupefilter/filtered": 939264, "elapsed_time_seconds": 330765.347056, "finish_reason": "finished", "finish_time": "2020-12-27 05:56:24.499766", "item_scraped_count": 7, "log_count/DEBUG": 54603, "log_count/ERROR": 13, "log_count/INFO": 5522, "memusage/max": 160956416, "memusage/startup": 60649472, "request_depth_max": 303, "response_received_count": 54277, "robotstxt/forbidden": 271, "robotstxt/request_count": 1, "robotstxt/response_count": 1, "robotstxt/response_status_count/200": 1, "scheduler/dequeued": 54594, "scheduler/dequeued/memory": 54594, "scheduler/enqueued": 54594, "scheduler/enqueued/memory": 54594, "spider_exceptions/JSONDecodeError": 13, "start_time": "2020-12-23 10:03:39.152710"}