{"downloader/exception_count": 5, "downloader/exception_type_count/twisted.internet.error.ConnectError": 2, "downloader/exception_type_count/twisted.internet.error.TCPTimedOutError": 3, "downloader/request_bytes": 2773502, "downloader/request_count": 6047, "downloader/request_method_count/GET": 6047, "downloader/response_bytes": 75085630, "downloader/response_count": 6042, "downloader/response_status_count/200": 6032, "downloader/response_status_count/301": 6, "downloader/response_status_count/404": 4, "dupefilter/filtered": 71081, "elapsed_time_seconds": 36768.486519, "finish_reason": "finished", "finish_time": "2021-02-19 22:36:44.182959", "log_count/DEBUG": 6050, "log_count/INFO": 622, "memusage/max": 85938176, "memusage/startup": 62308352, "offsite/domains": 2, "offsite/filtered": 5785, "request_depth_max": 38, "response_received_count": 6036, "retry/count": 5, "retry/reason_count/twisted.internet.error.ConnectError": 2, "retry/reason_count/twisted.internet.error.TCPTimedOutError": 3, "robotstxt/request_count": 1, "robotstxt/response_count": 1, "robotstxt/response_status_count/200": 1, "scheduler/dequeued": 6046, "scheduler/dequeued/memory": 6046, "scheduler/enqueued": 6046, "scheduler/enqueued/memory": 6046, "start_time": "2021-02-19 12:23:55.696440"}